newt/__init__.py
newt/common.py
newt/proxy_async.py
newt/proxy_sync.py
newt/queue.py
newt-0.1.0.dist-info/LICENSE
newt-0.1.0.dist-info/METADATA
newt-0.1.0.dist-info/WHEEL
newt-0.1.0.dist-info/top_level.txt
newt-0.1.0.dist-info/RECORD
