Metadata-Version: 2.1
Name: newt
Version: 0.1.0
Summary: Thread-safe, mixed sync-async queue for Python
Home-page: https://github.com/kaelzhang/python-newt
Author: kaelzhang
Author-email: 
License: MIT
Keywords: newt
Platform: UNKNOWN
Classifier: Topic :: Software Development :: Libraries :: Python Modules
Classifier: Programming Language :: Python :: 3.7
Classifier: Programming Language :: Python :: 3.8
Classifier: Programming Language :: Python :: Implementation :: PyPy
Classifier: Topic :: Software Development :: Libraries :: Python Modules
Classifier: License :: OSI Approved :: MIT License
Requires-Python: >=3.7
